airflow_cyberark_secrets_backend/__init__.py
airflow_cyberark_secrets_backend/cyberark_backend.py
airflow_cyberark_secrets_backend-0.1.0.dist-info/LICENSE
airflow_cyberark_secrets_backend-0.1.0.dist-info/METADATA
airflow_cyberark_secrets_backend-0.1.0.dist-info/WHEEL
airflow_cyberark_secrets_backend-0.1.0.dist-info/top_level.txt
airflow_cyberark_secrets_backend-0.1.0.dist-info/RECORD
