Metadata-Version: 2.1
Name: airflow-cyberark-secrets-backend
Version: 0.1.0
Summary: An Airflow custom secrets backend for CyberArk CCP
Home-page: https://github.com/jkornblum/airflow-cyberark-secrets-backend
Author: Joshua Kornblum
License: MIT
Platform: UNKNOWN
Requires-Python: >=3.6
Requires-Dist: apache-airflow (<3,>=1.10.10)
Provides-Extra: dev
Requires-Dist: bandit (==1.7.0) ; extra == 'dev'
Requires-Dist: black (==20.8b1) ; extra == 'dev'
Requires-Dist: pytest (==6.2.2) ; extra == 'dev'
Requires-Dist: pylint (==2.7.2) ; extra == 'dev'
Requires-Dist: safety (==1.10.3) ; extra == 'dev'
